libretranslatepy/__init__.py
libretranslatepy/api.py
libretranslatepy-2.1.3.dist-info/LICENSE
libretranslatepy-2.1.3.dist-info/METADATA
libretranslatepy-2.1.3.dist-info/WHEEL
libretranslatepy-2.1.3.dist-info/top_level.txt
libretranslatepy-2.1.3.dist-info/RECORD
