Metadata-Version: 2.1
Name: libretranslatepy
Version: 2.1.3
Summary: Python bindings for LibreTranslate API
Home-page: https://github.com/argosopentech/LibreTranslate-py
License: UNKNOWN
Project-URL: Bug Reports, https://github.com/argosopentech/LibreTranslate-py/issues
Project-URL: Source, https://github.com/argosopentech/LibreTranslate-py/
Keywords: translation libretranslate
Platform: UNKNOWN
Classifier: Development Status :: 5 - Production/Stable
Classifier: Topic :: Scientific/Engineering :: Interface Engine/Protocol Translator
Classifier: Intended Audience :: Developers
Classifier: License :: OSI Approved :: MIT License
Classifier: Programming Language :: Python :: 2
Classifier: Programming Language :: Python :: 3
Requires-Python: >=2.6
